odoo/addons/tracking_manager_domain/README.rst
odoo/addons/tracking_manager_domain/__init__.py
odoo/addons/tracking_manager_domain/__manifest__.py
odoo/addons/tracking_manager_domain/i18n/it.po
odoo/addons/tracking_manager_domain/i18n/tracking_manager_domain.pot
odoo/addons/tracking_manager_domain/models/__init__.py
odoo/addons/tracking_manager_domain/models/ir_model_fields.py
odoo/addons/tracking_manager_domain/models/models.py
odoo/addons/tracking_manager_domain/readme/CONTRIBUTORS.md
odoo/addons/tracking_manager_domain/readme/USAGE.md
odoo/addons/tracking_manager_domain/static/description/fields.drawio.png
odoo/addons/tracking_manager_domain/static/description/icon.png
odoo/addons/tracking_manager_domain/static/description/index.html
odoo/addons/tracking_manager_domain/tests/__init__.py
odoo/addons/tracking_manager_domain/tests/test_models.py
odoo/addons/tracking_manager_domain/views/ir_model_fields.xml
odoo_addon_tracking_manager_domain-18.0.1.0.1.dist-info/METADATA
odoo_addon_tracking_manager_domain-18.0.1.0.1.dist-info/WHEEL
odoo_addon_tracking_manager_domain-18.0.1.0.1.dist-info/top_level.txt
odoo_addon_tracking_manager_domain-18.0.1.0.1.dist-info/RECORD
