Metadata-Version: 2.1
Name: odoo-addon-tracking_manager_domain
Version: 18.0.1.0.1
Requires-Python: >=3.10
Requires-Dist: odoo-addon-tracking_manager==18.0.*
Requires-Dist: odoo==18.0.*
Summary: This module extends the tracking manager to allow to define a domain on fields to track changes only when certain conditions apply.
Home-page: https://github.com/OCA/server-tools
License: AGPL-3
Author: glueckkanja AG, Odoo Community Association (OCA)
Author-email: support@odoo-community.org
Classifier: Programming Language :: Python
Classifier: Framework :: Odoo
Classifier: Framework :: Odoo :: 18.0
Classifier: License :: OSI Approved :: GNU Affero General Public License v3
